llamadb/__init__.py
llamadb/api/__init__.py
llamadb/api/app.py
llamadb/cli/__init__.py
llamadb/cli/demo.py
llamadb/cli/main.py
llamadb/core/__init__.py
llamadb/core/accelerated_ops.py
llamadb/core/mlx_acceleration.py
llamadb/core/vector_index.py
llamadb/integrations/__init__.py
llamadb/integrations/anthropic/__init__.py
llamadb/integrations/anthropic/client.py
llamadb/integrations/anthropic/embeddings.py
llamadb/integrations/anthropic/pipeline.py
llamadb/utils/__init__.py
llamadb/utils/logging.py
llamadb_llamasearch-0.1.0.dist-info/licenses/LICENSE
llamadb_llamasearch-0.1.0.dist-info/METADATA
llamadb_llamasearch-0.1.0.dist-info/WHEEL
llamadb_llamasearch-0.1.0.dist-info/entry_points.txt
llamadb_llamasearch-0.1.0.dist-info/top_level.txt
llamadb_llamasearch-0.1.0.dist-info/RECORD
