Metadata-Version: 2.4
Name: llamadb-llamasearch
Version: 0.1.0
Summary: Next-Gen Hybrid Python/Rust Data Platform with MLX
Home-page: https://llamasearch.ai
Author: LlamaSearch AI
Author-email: llamadb-llamasearch <nikjois@llamasearch.ai>
License: Apache-2.0
Project-URL: Homepage, https://github.com/yourusername/llamadb
Project-URL: Documentation, https://github.com/yourusername/llamadb#readme
Project-URL: Repository, https://github.com/yourusername/llamadb.git
Project-URL: Issues, https://github.com/yourusername/llamadb/issues
Classifier: Development Status :: 4 - Beta
Classifier: Intended Audience :: Developers
Classifier: Intended Audience :: Science/Research
Classifier: License :: OSI Approved :: Apache Software License
Classifier: Programming Language :: Python :: 3
Classifier: Programming Language :: Python :: 3.11
Classifier: Programming Language :: Rust
Classifier: Topic :: Database
Classifier: Topic :: Scientific/Engineering :: Artificial Intelligence
Classifier: Topic :: Software Development :: Libraries :: Python Modules
Requires-Python: >=3.11
License-File: LICENSE
Requires-Dist: numpy>=1.24.0
Requires-Dist: pandas>=2.0.0
Requires-Dist: scipy>=1.10.0
Requires-Dist: scikit-learn>=1.2.0
Requires-Dist: fastapi>=0.115.0
Requires-Dist: uvicorn>=0.27.0
Requires-Dist: pydantic>=2.5.0
Requires-Dist: typer>=0.9.0
Requires-Dist: rich>=13.6.0
Requires-Dist: sqlalchemy>=2.0.0
Requires-Dist: python-dotenv>=1.0.0
Requires-Dist: pyyaml>=6.0.0
Requires-Dist: tqdm>=4.66.0
Provides-Extra: api
Requires-Dist: fastapi>=0.115.0; extra == "api"
Requires-Dist: uvicorn>=0.27.0; extra == "api"
Requires-Dist: pydantic>=2.5.0; extra == "api"
Requires-Dist: starlette>=0.35.0; extra == "api"
Requires-Dist: httpx>=0.25.0; extra == "api"
Provides-Extra: dev
Requires-Dist: black>=23.10.0; extra == "dev"
Requires-Dist: ruff>=0.1.0; extra == "dev"
Requires-Dist: mypy>=1.6.0; extra == "dev"
Requires-Dist: pre-commit>=3.5.0; extra == "dev"
Requires-Dist: ipython>=8.16.0; extra == "dev"
Provides-Extra: test
Requires-Dist: pytest>=7.4.0; extra == "test"
Requires-Dist: pytest-cov>=4.1.0; extra == "test"
Requires-Dist: pytest-benchmark>=4.0.0; extra == "test"
Provides-Extra: docs
Requires-Dist: sphinx>=7.2.0; extra == "docs"
Requires-Dist: sphinx-rtd-theme>=1.3.0; extra == "docs"
Requires-Dist: sphinx-autodoc-typehints>=1.24.0; extra == "docs"
Requires-Dist: nbsphinx>=0.9.0; extra == "docs"
Requires-Dist: myst-parser>=2.0.0; extra == "docs"
Provides-Extra: mlx
Requires-Dist: mlx>=0.5.0; extra == "mlx"
Provides-Extra: full
Requires-Dist: llamadb[api,dev,docs,mlx,test]; extra == "full"
Dynamic: author
Dynamic: home-page
Dynamic: license-file
Dynamic: requires-python
